PyXenApi/__init__.py
PyXenApi/xenforoapi.py
pyxenapi-1.0.0.dist-info/WHEEL
pyxenapi-1.0.0.dist-info/METADATA
pyxenapi-1.0.0.dist-info/RECORD
